image_ema_project/__init__.py
image_ema_project/__main__.py
image_ema_project/core.py
image_ema_project/visualize.py
image_ema_project_test1-0.0.1.dist-info/License
image_ema_project_test1-0.0.1.dist-info/METADATA
image_ema_project_test1-0.0.1.dist-info/WHEEL
image_ema_project_test1-0.0.1.dist-info/top_level.txt
image_ema_project_test1-0.0.1.dist-info/RECORD
