Metadata-Version: 2.1
Name: image-ema-project-test1
Version: 0.0.1
Summary: A simple example project for the 2019 High-speed Image Based Experimental Modal Analysis & Open Source Tools Summer School.
Home-page: https://github.com/ladisk/image-ema-2019-project
Author: Janko Slavič, Domen Gorjup, Klemen Zaletelj
Author-email: janko.slavic@fs.uni-lj.si
Maintainer: Janko Slavič, Domen Gorjup, Klemen Zaletelj
Maintainer-email: janko.slavic@fs.uni-lj.si
License: MIT license
Keywords: Image-EMA Summer School
Platform: UNKNOWN
Classifier: Development Status :: 3 - Alpha
Classifier: Intended Audience :: Developers
Classifier: Programming Language :: Python :: 3.6
Requires-Dist: numpy (>=1.11.0)
Requires-Dist: scipy (>=1.2.0)
Requires-Dist: matplotlib (>=3.0.0)
Requires-Dist: pyMRAW (>=0.2.0)
Requires-Dist: tqdm (>=4.25.0)
